[
  {
    "id": 1,
    "nome": "Arroz",
    "preco": 13.99
  },
  {
    "id": 2,
    "nome": "Feijão",
    "preco": 14.99
  },
  {
    "id": 3,
    "nome": "Batata",
    "preco": 20.99
  },
  {
    "id": 4,
    "nome": "Café",
    "preco": 39.99
  },
  {
    "id": 5,
    "nome": "Suco de laranja",
    "preco": 5.99
  },
  {
    "id": 6,
    "nome": "Suco de manga",
    "preco": 5.99
  },
  {
    "id": 7,
    "nome": "Chocolate",
    "preco": 6.99
  },
  {
    "id": 8,
    "nome": "Bola de futebol",
    "preco": 70.99
  },
  {
    "id": 9,
    "nome": "pão",
    "preco": 0.99
  }
]